{
  "ticker": "TQQQ",
  "status": "active",
  "cycleNumber": 1,
  "strategyVersion": "v2.2",
  "splitCount": 40,
  "targetProfit": 0.1,
  "starDecreaseRate": 0.005,
  "principal": 13123,
  "buyPerRound": 328.075,
  "totalQuantity": 15,
  "avgPrice": 59.1904,
  "totalInvested": 887.856,
  "remainingCash": 12235.144,
  "totalBuyAmount": 1288.86,
  "totalSellAmount": 438.15999999999997,
  "totalRealizedProfit": -850.6999999999999,
  "startedAt": "2026-04-15T14:04:33.334Z",
  "updatedAt": "2026-04-30T22:00:04.293Z",
  "currentPrice": 63.54,
  "unrealizedPnl": 65.24400000000003,
  "unrealizedPnlRate": 0.0734848894415311
}
