{
  "ticker": "TQQQ",
  "status": "active",
  "cycleNumber": 3,
  "strategyVersion": "v2.2",
  "splitCount": 40,
  "targetProfit": 0.15,
  "starDecreaseRate": 0.0075,
  "principal": 13338.6499,
  "buyPerRound": 333.4662475,
  "totalQuantity": 96,
  "avgPrice": 73.53,
  "totalInvested": 7058.88,
  "remainingCash": 6279.7699,
  "totalBuyAmount": 8360.330000000002,
  "totalSellAmount": 1457.25,
  "totalRealizedProfit": -6903.080000000002,
  "startedAt": "2026-05-11T14:00:04.878Z",
  "updatedAt": "2026-07-23T22:00:07.605Z",
  "currentPrice": 66.3,
  "unrealizedPnl": -694.0800000000004,
  "unrealizedPnlRate": -0.098327213382293
}
